pytest_autofixture/__init__.py
pytest_autofixture-0.2.1.dist-info/LICENSE.txt
pytest_autofixture-0.2.1.dist-info/METADATA
pytest_autofixture-0.2.1.dist-info/WHEEL
pytest_autofixture-0.2.1.dist-info/entry_points.txt
pytest_autofixture-0.2.1.dist-info/top_level.txt
pytest_autofixture-0.2.1.dist-info/RECORD
