Metadata-Version: 2.1
Name: pytest-autofixture
Version: 0.2.1
Summary: simplify pytest fixtures
Author: Daniel Pepper
License: The MIT License (MIT)
Project-URL: Homepage, https://github.com/dpep/pytest-autofixture
Classifier: Framework :: Pytest
Classifier: License :: OSI Approved :: MIT License
Classifier: Topic :: Software Development :: Testing
Requires-Python: >=3
License-File: LICENSE.txt
Requires-Dist: pytest >=8
Provides-Extra: test
Requires-Dist: isort >=5.13 ; extra == 'test'
Requires-Dist: setuptools >=61 ; extra == 'test'
